odoo/addons/stock_account_inventory_discrepancy/README.rst
odoo/addons/stock_account_inventory_discrepancy/__init__.py
odoo/addons/stock_account_inventory_discrepancy/__manifest__.py
odoo/addons/stock_account_inventory_discrepancy/i18n/stock_account_inventory_discrepancy.pot
odoo/addons/stock_account_inventory_discrepancy/models/__init__.py
odoo/addons/stock_account_inventory_discrepancy/models/stock_inventory_line.py
odoo/addons/stock_account_inventory_discrepancy/models/stock_location.py
odoo/addons/stock_account_inventory_discrepancy/models/stock_warehouse.py
odoo/addons/stock_account_inventory_discrepancy/readme/CONFIGURE.rst
odoo/addons/stock_account_inventory_discrepancy/readme/CONTRIBUTORS.rst
odoo/addons/stock_account_inventory_discrepancy/readme/DESCRIPTION.rst
odoo/addons/stock_account_inventory_discrepancy/static/description/icon.png
odoo/addons/stock_account_inventory_discrepancy/static/description/index.html
odoo/addons/stock_account_inventory_discrepancy/tests/__init__.py
odoo/addons/stock_account_inventory_discrepancy/tests/test_inventory_discrepancy.py
odoo/addons/stock_account_inventory_discrepancy/views/stock_inventory_view.xml
odoo/addons/stock_account_inventory_discrepancy/views/stock_location_view.xml
odoo/addons/stock_account_inventory_discrepancy/views/stock_warehouse_view.xml
odoo12_addon_stock_account_inventory_discrepancy-12.0.1.0.0.99.dev3.dist-info/METADATA
odoo12_addon_stock_account_inventory_discrepancy-12.0.1.0.0.99.dev3.dist-info/WHEEL
odoo12_addon_stock_account_inventory_discrepancy-12.0.1.0.0.99.dev3.dist-info/top_level.txt
odoo12_addon_stock_account_inventory_discrepancy-12.0.1.0.0.99.dev3.dist-info/RECORD
